Metadata-Version: 2.1
Name: vertx-eventbus-client
Version: 1.0.0
Summary: Vertx EventBus Client
Home-page: https://github.com/vert-x3/vertx-eventbus-bridge-clients/tree/master/python
Author: vertx-dev
Author-email: vertx-dev@googlegroups.com
License: Apache Software License 2.0
Platform: UNKNOWN
